LICENSE
MANIFEST.in
README.rst
setup.cfg
setup.py
aioli_sphinx_theme.egg-info/PKG-INFO
aioli_sphinx_theme.egg-info/SOURCES.txt
aioli_sphinx_theme.egg-info/dependency_links.txt
aioli_sphinx_theme.egg-info/entry_points.txt
aioli_sphinx_theme.egg-info/top_level.txt
alabaster/__init__.py
alabaster/_version.py
alabaster/about.html
alabaster/custom.css
alabaster/donate.html
alabaster/layout.html
alabaster/navigation.html
alabaster/relations.html
alabaster/support.py
alabaster/theme.conf
alabaster/__pycache__/__init__.cpython-37.pyc
alabaster/__pycache__/_version.cpython-37.pyc
alabaster/static/alabaster.css_t
alabaster/static/custom.css