Metadata-Version: 1.0
Name: aioli-sphinx-theme
Version: 0.7.13.2
Summary: Aioli Sphinx theme, based on Alabaster
Home-page: https://alabaster.readthedocs.io
Author: Robert Wikman
Author-email: rbw@vault13.org
License: UNKNOWN
Platform: UNKNOWN
